sourcetypes.py
sourcetypes-0.0.4.dist-info/LICENSE
sourcetypes-0.0.4.dist-info/METADATA
sourcetypes-0.0.4.dist-info/WHEEL
sourcetypes-0.0.4.dist-info/top_level.txt
sourcetypes-0.0.4.dist-info/RECORD
