Metadata-Version: 2.1
Name: sourcetypes
Version: 0.0.4
Summary: Python Source Code Types For Inline Syntax Highlighting
Home-page: https://github.com/samwillis/python-inline-source/sourcetypes
Author: Sam Willis
License: UNKNOWN
Platform: UNKNOWN
Classifier: Programming Language :: Python :: 3
Classifier: License :: OSI Approved :: MIT License
Classifier: Operating System :: OS Independent
Requires-Python: >=3.7
Requires-Dist: typing-extensions (>=3.7.4)
